{
    "generated": "2026-03-29T07:12:54.779997+00:00",
    "packages": [
        {
            "exportCount": 0,
            "name": "macroforge",
            "version": "0.1.77"
        },
        {
            "exportCount": 16,
            "name": "@macroforge/shared",
            "version": "0.1.77"
        },
        {
            "exportCount": 2,
            "name": "@macroforge/vite-plugin",
            "version": "0.1.77"
        },
        {
            "exportCount": 1,
            "name": "@macroforge/typescript-plugin",
            "version": "0.1.77"
        },
        {
            "exportCount": 5,
            "name": "@macroforge/svelte-language-server",
            "version": "0.1.77"
        },
        {
            "exportCount": 3,
            "name": "@macroforge/svelte-preprocessor",
            "version": "0.1.77"
        },
        {
            "exportCount": 1,
            "name": "@macroforge/mcp-server",
            "version": "0.1.77"
        }
    ]
}
